CHANGES.txt
MANIFEST.in
README.rst
bootstrap.py
buildout.cfg
setup.py
collective/__init__.py
collective.weightedportlets.egg-info/PKG-INFO
collective.weightedportlets.egg-info/SOURCES.txt
collective.weightedportlets.egg-info/dependency_links.txt
collective.weightedportlets.egg-info/entry_points.txt
collective.weightedportlets.egg-info/namespace_packages.txt
collective.weightedportlets.egg-info/not-zip-safe
collective.weightedportlets.egg-info/requires.txt
collective.weightedportlets.egg-info/top_level.txt
collective/weightedportlets/__init__.py
collective/weightedportlets/configure.zcml
collective/weightedportlets/editmanager.py
collective/weightedportlets/exportimport.py
collective/weightedportlets/interfaces.py
collective/weightedportlets/retriever.py
collective/weightedportlets/testing.py
collective/weightedportlets/upgrades.zcml
collective/weightedportlets/utils.py
collective/weightedportlets/Extensions/Install.py
collective/weightedportlets/browser/__init__.py
collective/weightedportlets/browser/configure.zcml
collective/weightedportlets/browser/javascripts/weightedportlets.js
collective/weightedportlets/profiles/default/browserlayer.xml
collective/weightedportlets/profiles/default/componentregistry.xml
collective/weightedportlets/profiles/default/jsregistry.xml
collective/weightedportlets/profiles/default/metadata.xml
collective/weightedportlets/tests/__init__.py
collective/weightedportlets/tests/test_doctest.py
collective/weightedportlets/tests/weights.txt
docs/INSTALL.txt
docs/LICENSE.GPL
docs/LICENSE.txt