Metadata-Version: 1.1
Name: collective.weightedportlets
Version: 1.2
Summary: Adds the ability to tweak portlet ordering by giving each portlet a weight.
Home-page: http://plone.org/products/collective.weightedportlets
Author: David Glick
Author-email: david@glicksoftware.com
License: GPL
Keywords: plone portlets
Platform: UNKNOWN
Classifier: Framework :: Plone
Classifier: Intended Audience :: Developers
Classifier: Topic :: Software Development :: Libraries :: Python Modules
Classifier: License :: OSI Approved :: GNU General Public License (GPL)
